setup.py
distributions_prob2022/Binomialdistribution.py
distributions_prob2022/Gaussiandistribution.py
distributions_prob2022/Generaldistribution.py
distributions_prob2022/__init__.py
distributions_prob2022.egg-info/PKG-INFO
distributions_prob2022.egg-info/SOURCES.txt
distributions_prob2022.egg-info/dependency_links.txt
distributions_prob2022.egg-info/not-zip-safe
distributions_prob2022.egg-info/top_level.txt