Metadata-Version: 1.0
Name: distributions-prob2022
Version: 1.0
Summary: Gaussian distributions and Binomial disributions
Home-page: UNKNOWN
Author: James Mugwanya
Author-email: jamesmugwanya90@gmail.com
License: UNKNOWN
Platform: UNKNOWN
